{
  "id": "en_tier1_lesson_42",
  "tier": "en_tier1",
  "lesson_number": 42,
  "title": "Capital letters and Shift patterns",
  "description": "Mixed case typing — Shift held for caps, released for lower",
  "target_wpm": 30,
  "text_length": 140,
  "error_limit_percent": 9,
  "error_limit": 12,
  "text": "London, Paris, New York, Tokyo. The CEO of TechCorp said: \"AI will change SaaS, IoT, and ML.\" Alice Brown won the Nobel Prize.",
  "text_sequence": [],
  "keys_trained": [
    "A-Z (lower)",
    "A-Z (upper)",
    "0-9",
    ".",
    ",",
    ":",
    "\"",
    "Space",
    "Shift"
  ],
  "new_keys": [],
  "finger_focus": "Shift + letter for capitals — opposite-hand Shift rule",
  "tips": [
    {
      "type": "lead",
      "text": "For a capital, reach the Shift with the opposite hand. The letter's hand stays free to strike."
    },
    {
      "type": "drop",
      "text": "A sits under the left pinky, so the right Shift carries it. Let the hands divide the work."
    },
    {
      "type": "exercise",
      "target": "London, Paris, New York, Tokyo. The CEO of TechCorp said: \"AI",
      "finger": "blue",
      "hint": "Shift + letter for capitals - opposite-hand Shift rule"
    },
    {
      "type": "p",
      "text": "L lives under the right ring finger, so the left Shift takes it. The rule is the same, mirrored."
    },
    {
      "type": "callout",
      "icon": "💡",
      "title": "Note",
      "text": "For an acronym - CEO, AI, SaaS - hold the Shift down through the whole word rather than tapping it letter by letter."
    },
    {
      "type": "exercise",
      "target": "will change SaaS, IoT, and ML.\" Alice Brown won the Nobel Prize.",
      "finger": "green",
      "hint": "Shift + letter for capitals - opposite-hand Shift rule"
    }
  ],
  "character_tips": {
    "anna": "Capitals reward a smooth Shift. Opposite hand every time, and the rhythm never breaks.",
    "maxim": "Names, places, acronyms - capitals run through everything you write at work. Drill the reach.",
    "knopych": "Opposite-hand Shift. Once it's reflex, the big letters cost you nothing.",
    "klavochka": "Tall letters and small ones, side by side, in step. Keep the line even."
  },
  "phase": 3,
  "rhythmLesson": false,
  "created_at": "2026-05-25",
  "version": "1.0"
}
