{
  "id": "en_tier1_lesson_15",
  "tier": "en_tier1",
  "lesson_number": 15,
  "title": "BLOCK 1 FINAL: Alphabet mastery test",
  "description": "Closing test for Block 1 — full alphabet, sentences, 25 WPM target",
  "target_wpm": 25,
  "text_length": 100,
  "error_limit_percent": 7,
  "error_limit": 7,
  "text": "the quick brown fox jumps over the lazy dog and watches the river flow under a wide blue sky",
  "text_sequence": [],
  "keys_trained": [
    "A",
    "B",
    "C",
    "D",
    "E",
    "F",
    "G",
    "H",
    "I",
    "J",
    "K",
    "L",
    "M",
    "N",
    "O",
    "P",
    "Q",
    "R",
    "S",
    "T",
    "U",
    "V",
    "W",
    "X",
    "Y",
    "Z",
    "Space"
  ],
  "new_keys": [],
  "finger_focus": "Whole alphabet — speed + accuracy gate",
  "tips": [
    {
      "type": "lead",
      "text": "This is the closing test for the block. The old fox carries every one of the twenty-six letters, and the line that follows asks for all of them again. Type it like proof."
    },
    {
      "type": "drop",
      "text": "Clear this line and the alphabet is yours. From here on there is no English sentence you cannot set down."
    },
    {
      "type": "exercise",
      "target": "the quick brown fox jumps over the lazy dog",
      "finger": "blue",
      "hint": "Whole alphabet - speed + accuracy gate"
    },
    {
      "type": "p",
      "text": "The mark is twenty-five words a minute with fewer than seven slips. Hold your pace; do not chase the number."
    },
    {
      "type": "exercise",
      "target": "and watches the river flow under a wide blue sky",
      "finger": "green",
      "hint": "Whole alphabet - speed + accuracy gate"
    }
  ],
  "character_tips": {
    "anna": "This is the test that closes the block. Pass it and the alphabet belongs to you. Punctuation is the next desk over. - Eleanor Hayes, editor",
    "maxim": "End of the first block. Any English word will go under your hands now. Next we add the marks that turn words into proper copy. - Eleanor Hayes, editor",
    "knopych": "One clean line stands between you and the next block. Keep your rhythm and walk through it. - Eleanor Hayes, editor",
    "klavochka": "The last test of the block, and you have earned your way to it. Steady hands, clear head. You can do this. - Eleanor Hayes, editor"
  },
  "phase": 1,
  "rhythmLesson": false,
  "created_at": "2026-05-25",
  "version": "1.0"
}
