{
  "id": "ru_kids_lesson_10",
  "tier": "ru_kids",
  "lesson_number": 10,
  "title": "БЛОК 1 ФИНАЛ: домашний ряд",
  "description": "Тест всего домашнего ряда: А О В Л Ы Д Ф Ж.",
  "target_wpm": 18,
  "text_length": 48,
  "error_limit_percent": 10,
  "error_limit": 3,
  "text": "жало ждал лажа жажда вода дала овал вол лады лад",
  "text_sequence": [
    {
      "char": "ж",
      "hand": "right",
      "finger": "pinky",
      "key": "Ж"
    },
    {
      "char": "а",
      "hand": "left",
      "finger": "index",
      "key": "А"
    },
    {
      "char": "л",
      "hand": "right",
      "finger": "middle",
      "key": "Л"
    },
    {
      "char": "о",
      "hand": "right",
      "finger": "index",
      "key": "О"
    },
    {
      "char": " ",
      "hand": "left",
      "finger": "thumb",
      "key": "Space",
      "space_side": "left"
    },
    {
      "char": "ж",
      "hand": "right",
      "finger": "pinky",
      "key": "Ж"
    },
    {
      "char": "д",
      "hand": "right",
      "finger": "ring",
      "key": "Д"
    },
    {
      "char": "а",
      "hand": "left",
      "finger": "index",
      "key": "А"
    },
    {
      "char": "л",
      "hand": "right",
      "finger": "middle",
      "key": "Л"
    },
    {
      "char": " ",
      "hand": "left",
      "finger": "thumb",
      "key": "Space",
      "space_side": "left"
    },
    {
      "char": "л",
      "hand": "right",
      "finger": "middle",
      "key": "Л"
    },
    {
      "char": "а",
      "hand": "left",
      "finger": "index",
      "key": "А"
    },
    {
      "char": "ж",
      "hand": "right",
      "finger": "pinky",
      "key": "Ж"
    },
    {
      "char": "а",
      "hand": "left",
      "finger": "index",
      "key": "А"
    },
    {
      "char": " ",
      "hand": "left",
      "finger": "thumb",
      "key": "Space",
      "space_side": "left"
    },
    {
      "char": "ж",
      "hand": "right",
      "finger": "pinky",
      "key": "Ж"
    },
    {
      "char": "а",
      "hand": "left",
      "finger": "index",
      "key": "А"
    },
    {
      "char": "ж",
      "hand": "right",
      "finger": "pinky",
      "key": "Ж"
    },
    {
      "char": "д",
      "hand": "right",
      "finger": "ring",
      "key": "Д"
    },
    {
      "char": "а",
      "hand": "left",
      "finger": "index",
      "key": "А"
    },
    {
      "char": " ",
      "hand": "right",
      "finger": "thumb",
      "key": "Space",
      "space_side": "right"
    },
    {
      "char": "в",
      "hand": "left",
      "finger": "middle",
      "key": "В"
    },
    {
      "char": "о",
      "hand": "right",
      "finger": "index",
      "key": "О"
    },
    {
      "char": "д",
      "hand": "right",
      "finger": "ring",
      "key": "Д"
    },
    {
      "char": "а",
      "hand": "left",
      "finger": "index",
      "key": "А"
    },
    {
      "char": " ",
      "hand": "left",
      "finger": "thumb",
      "key": "Space",
      "space_side": "left"
    },
    {
      "char": "д",
      "hand": "right",
      "finger": "ring",
      "key": "Д"
    },
    {
      "char": "а",
      "hand": "left",
      "finger": "index",
      "key": "А"
    },
    {
      "char": "л",
      "hand": "right",
      "finger": "middle",
      "key": "Л"
    },
    {
      "char": "а",
      "hand": "left",
      "finger": "index",
      "key": "А"
    },
    {
      "char": " ",
      "hand": "left",
      "finger": "thumb",
      "key": "Space",
      "space_side": "left"
    },
    {
      "char": "о",
      "hand": "right",
      "finger": "index",
      "key": "О"
    },
    {
      "char": "в",
      "hand": "left",
      "finger": "middle",
      "key": "В"
    },
    {
      "char": "а",
      "hand": "left",
      "finger": "index",
      "key": "А"
    },
    {
      "char": "л",
      "hand": "right",
      "finger": "middle",
      "key": "Л"
    },
    {
      "char": " ",
      "hand": "right",
      "finger": "thumb",
      "key": "Space",
      "space_side": "right"
    },
    {
      "char": "в",
      "hand": "left",
      "finger": "middle",
      "key": "В"
    },
    {
      "char": "о",
      "hand": "right",
      "finger": "index",
      "key": "О"
    },
    {
      "char": "л",
      "hand": "right",
      "finger": "middle",
      "key": "Л"
    },
    {
      "char": " ",
      "hand": "left",
      "finger": "thumb",
      "key": "Space",
      "space_side": "left"
    },
    {
      "char": "л",
      "hand": "right",
      "finger": "middle",
      "key": "Л"
    },
    {
      "char": "а",
      "hand": "left",
      "finger": "index",
      "key": "А"
    },
    {
      "char": "д",
      "hand": "right",
      "finger": "ring",
      "key": "Д"
    },
    {
      "char": "ы",
      "hand": "left",
      "finger": "ring",
      "key": "Ы"
    },
    {
      "char": " ",
      "hand": "left",
      "finger": "thumb",
      "key": "Space",
      "space_side": "left"
    },
    {
      "char": "л",
      "hand": "right",
      "finger": "middle",
      "key": "Л"
    },
    {
      "char": "а",
      "hand": "left",
      "finger": "index",
      "key": "А"
    },
    {
      "char": "д",
      "hand": "right",
      "finger": "ring",
      "key": "Д"
    }
  ],
  "keys_trained": [
    "А",
    "О",
    "В",
    "Л",
    "Ы",
    "Д",
    "Ф",
    "Ж",
    "Space"
  ],
  "new_keys": [],
  "finger_focus": "Знакомые буквы домашнего ряда",
  "tips": [
    {
      "type": "lead",
      "text": "Самый главный урок! Покажем весь наш домашний ряд 🏆"
    },
    {
      "type": "drop",
      "text": "Тут живут все восемь буковок: А О В Л Ы Д Ф Ж. Ты их уже знаешь 🌸"
    },
    {
      "type": "exercise",
      "target": "жало жажда вода",
      "finger": "pink",
      "hint": "Не спеши, ты всё это уже умеешь"
    },
    {
      "type": "p",
      "text": "Какой ты молодец, выучил весь домашний ряд! Теперь у тебя есть крепкий домик для пальчиков 🏠"
    },
    {
      "type": "exercise",
      "target": "дала овал вол лады",
      "finger": "orange",
      "hint": "Последние словечки - и готово!"
    }
  ],
  "character_tips": {
    "anna": "Самый главный урок! Ты выучил весь домашний ряд, умница 🏆🌷",
    "maxim": "Не торопись. Ты уже знаешь все буковки: А О В Л Ы Д Ф Ж.",
    "knopych": "Ура! Весь домашний ряд теперь твой! Какой ты молодец 🏆",
    "klavochka": "Ты прошёл первый шаг, солнышко! Весь домашний рядок - твой 🏠💕"
  },
  "phase": 1,
  "rhythmLesson": false,
  "created_at": "2026-05-26",
  "version": "2.0"
}