{
  "id": "ru_teen_lesson_62",
  "tier": "ru_teen",
  "lesson_number": 62,
  "title": "Эссе: основной абзац",
  "description": "Аргумент-абзац с примерами",
  "target_wpm": 87,
  "text_length": 224,
  "error_limit_percent": 4,
  "error_limit": 8,
  "text": "Один яркий пример этого тренда — рост платформ короткого видео, которые трансформировали не только развлечения, но и то, как студенты учатся, делятся информацией и даже подают заявления на работу в современном рабочем месте.",
  "text_sequence": [],
  "keys_trained": [
    "А-Я",
    "Shift",
    "Space",
    ",",
    ".",
    "-"
  ],
  "new_keys": [],
  "finger_focus": "Ритм основного абзаца",
  "tips": [
    {
      "type": "lead",
      "text": "Структура аргумента: тезис + пример + влияние"
    },
    {
      "type": "drop",
      "text": "Длинные плавные предложения"
    },
    {
      "type": "exercise",
      "target": "Один яркий пример этого тренда — рост платформ короткого видео, которые трансформировали не только развлечения, но",
      "finger": "purple",
      "hint": "Ритм основного абзаца"
    },
    {
      "type": "p",
      "text": "Реальный темп эссе"
    },
    {
      "type": "exercise",
      "target": "и то, как студенты учатся, делятся информацией и даже подают заявления на работу в современном рабочем месте.",
      "finger": "purple",
      "hint": "Ритм основного абзаца"
    }
  ],
  "character_tips": {
    "anna": "Структура основного абзаца. Реальный формат эссе на скорости.",
    "maxim": "Аргументная проза = твой реальный голос. Тренируй.",
    "knopych": "📝 СИЛА ЭССЕ! Делай пойнт!",
    "klavochka": "Строишь сильный аргумент, моё сокровище 🏛️"
  },
  "phase": 5,
  "rhythmLesson": false,
  "created_at": "2026-05-26",
  "version": "1.0"
}
