{
  "id": "en_teen_lesson_75",
  "tier": "en_teen",
  "lesson_number": 75,
  "title": "TEEN COURSE FINAL: Tournament + certificate",
  "description": "The final teen exam - 95 WPM on a comprehensive mixed real-world paragraph. Pass earns the Teen Mastery certificate.",
  "target_wpm": 95,
  "text_length": 339,
  "error_limit_percent": 4,
  "error_limit": 13,
  "text": "Seventy-five lessons ago, the keyboard was a puzzle. Today, it's an extension of your thinking. You can write essays in minutes, send messages faster than you can speak, and keep up with any deadline. This final passage is the gate - long, dense, mixed content at 95 WPM. Pass it, and the Teen Mastery certificate is yours. Type with care.",
  "text_sequence": [
    {"char": "S", "hand": "left", "finger": "ring", "key": "S"},
    {"char": "e", "hand": "left", "finger": "middle", "key": "E"},
    {"char": "v", "hand": "left", "finger": "index", "key": "V"},
    {"char": "e", "hand": "left", "finger": "middle", "key": "E"},
    {"char": "n", "hand": "right", "finger": "index", "key": "N"},
    {"char": "t", "hand": "left", "finger": "index", "key": "T"},
    {"char": "y", "hand": "right", "finger": "index", "key": "Y"},
    {"char": "-", "hand": "right", "finger": "pinky", "key": "-"},
    {"char": "f", "hand": "left", "finger": "index", "key": "F"},
    {"char": "i", "hand": "right", "finger": "middle", "key": "I"},
    {"char": "v", "hand": "left", "finger": "index", "key": "V"},
    {"char": "e", "hand": "left", "finger": "middle", "key": "E"},
    {"char": " ", "hand": "right", "finger": "thumb", "key": "Space", "space_side": "right"},
    {"char": "l", "hand": "right", "finger": "ring", "key": "L"},
    {"char": "e", "hand": "left", "finger": "middle", "key": "E"},
    {"char": "s", "hand": "left", "finger": "ring", "key": "S"},
    {"char": "s", "hand": "left", "finger": "ring", "key": "S"},
    {"char": "o", "hand": "right", "finger": "ring", "key": "O"},
    {"char": "n", "hand": "right", "finger": "index", "key": "N"},
    {"char": "s", "hand": "left", "finger": "ring", "key": "S"},
    {"char": " ", "hand": "right", "finger": "thumb", "key": "Space", "space_side": "right"},
    {"char": "a", "hand": "left", "finger": "pinky", "key": "A"},
    {"char": "g", "hand": "left", "finger": "index", "key": "G"},
    {"char": "o", "hand": "right", "finger": "ring", "key": "O"},
    {"char": ",", "hand": "right", "finger": "middle", "key": ","},
    {"char": " ", "hand": "left", "finger": "thumb", "key": "Space", "space_side": "left"},
    {"char": "t", "hand": "left", "finger": "index", "key": "T"},
    {"char": "h", "hand": "right", "finger": "index", "key": "H"},
    {"char": "e", "hand": "left", "finger": "middle", "key": "E"},
    {"char": " ", "hand": "right", "finger": "thumb", "key": "Space", "space_side": "right"},
    {"char": "k", "hand": "right", "finger": "middle", "key": "K"},
    {"char": "e", "hand": "left", "finger": "middle", "key": "E"},
    {"char": "y", "hand": "right", "finger": "index", "key": "Y"},
    {"char": "b", "hand": "left", "finger": "index", "key": "B"},
    {"char": "o", "hand": "right", "finger": "ring", "key": "O"},
    {"char": "a", "hand": "left", "finger": "pinky", "key": "A"},
    {"char": "r", "hand": "left", "finger": "index", "key": "R"},
    {"char": "d", "hand": "left", "finger": "middle", "key": "D"},
    {"char": " ", "hand": "right", "finger": "thumb", "key": "Space", "space_side": "right"},
    {"char": "w", "hand": "left", "finger": "ring", "key": "W"},
    {"char": "a", "hand": "left", "finger": "pinky", "key": "A"},
    {"char": "s", "hand": "left", "finger": "ring", "key": "S"},
    {"char": " ", "hand": "right", "finger": "thumb", "key": "Space", "space_side": "right"},
    {"char": "a", "hand": "left", "finger": "pinky", "key": "A"},
    {"char": " ", "hand": "right", "finger": "thumb", "key": "Space", "space_side": "right"},
    {"char": "p", "hand": "right", "finger": "pinky", "key": "P"},
    {"char": "u", "hand": "right", "finger": "index", "key": "U"},
    {"char": "z", "hand": "left", "finger": "pinky", "key": "Z"},
    {"char": "z", "hand": "left", "finger": "pinky", "key": "Z"},
    {"char": "l", "hand": "right", "finger": "ring", "key": "L"},
    {"char": "e", "hand": "left", "finger": "middle", "key": "E"},
    {"char": ".", "hand": "right", "finger": "ring", "key": "."},
    {"char": " ", "hand": "left", "finger": "thumb", "key": "Space", "space_side": "left"},
    {"char": "T", "hand": "left", "finger": "index", "key": "T"},
    {"char": "o", "hand": "right", "finger": "ring", "key": "O"},
    {"char": "d", "hand": "left", "finger": "middle", "key": "D"},
    {"char": "a", "hand": "left", "finger": "pinky", "key": "A"},
    {"char": "y", "hand": "right", "finger": "index", "key": "Y"},
    {"char": ",", "hand": "right", "finger": "middle", "key": ","},
    {"char": " ", "hand": "left", "finger": "thumb", "key": "Space", "space_side": "left"},
    {"char": "i", "hand": "right", "finger": "middle", "key": "I"},
    {"char": "t", "hand": "left", "finger": "index", "key": "T"},
    {"char": "'", "hand": "right", "finger": "pinky", "key": "'"},
    {"char": "s", "hand": "left", "finger": "ring", "key": "S"},
    {"char": " ", "hand": "right", "finger": "thumb", "key": "Space", "space_side": "right"},
    {"char": "a", "hand": "left", "finger": "pinky", "key": "A"},
    {"char": "n", "hand": "right", "finger": "index", "key": "N"},
    {"char": " ", "hand": "left", "finger": "thumb", "key": "Space", "space_side": "left"},
    {"char": "e", "hand": "left", "finger": "middle", "key": "E"},
    {"char": "x", "hand": "left", "finger": "ring", "key": "X"},
    {"char": "t", "hand": "left", "finger": "index", "key": "T"},
    {"char": "e", "hand": "left", "finger": "middle", "key": "E"},
    {"char": "n", "hand": "right", "finger": "index", "key": "N"},
    {"char": "s", "hand": "left", "finger": "ring", "key": "S"},
    {"char": "i", "hand": "right", "finger": "middle", "key": "I"},
    {"char": "o", "hand": "right", "finger": "ring", "key": "O"},
    {"char": "n", "hand": "right", "finger": "index", "key": "N"},
    {"char": " ", "hand": "left", "finger": "thumb", "key": "Space", "space_side": "left"},
    {"char": "o", "hand": "right", "finger": "ring", "key": "O"},
    {"char": "f", "hand": "left", "finger": "index", "key": "F"},
    {"char": " ", "hand": "right", "finger": "thumb", "key": "Space", "space_side": "right"},
    {"char": "y", "hand": "right", "finger": "index", "key": "Y"},
    {"char": "o", "hand": "right", "finger": "ring", "key": "O"},
    {"char": "u", "hand": "right", "finger": "index", "key": "U"},
    {"char": "r", "hand": "left", "finger": "index", "key": "R"},
    {"char": " ", "hand": "right", "finger": "thumb", "key": "Space", "space_side": "right"},
    {"char": "t", "hand": "left", "finger": "index", "key": "T"},
    {"char": "h", "hand": "right", "finger": "index", "key": "H"},
    {"char": "i", "hand": "right", "finger": "middle", "key": "I"},
    {"char": "n", "hand": "right", "finger": "index", "key": "N"},
    {"char": "k", "hand": "right", "finger": "middle", "key": "K"},
    {"char": "i", "hand": "right", "finger": "middle", "key": "I"},
    {"char": "n", "hand": "right", "finger": "index", "key": "N"},
    {"char": "g", "hand": "left", "finger": "index", "key": "G"},
    {"char": ".", "hand": "right", "finger": "ring", "key": "."},
    {"char": " ", "hand": "left", "finger": "thumb", "key": "Space", "space_side": "left"},
    {"char": "Y", "hand": "right", "finger": "index", "key": "Y"},
    {"char": "o", "hand": "right", "finger": "ring", "key": "O"},
    {"char": "u", "hand": "right", "finger": "index", "key": "U"},
    {"char": " ", "hand": "left", "finger": "thumb", "key": "Space", "space_side": "left"},
    {"char": "c", "hand": "left", "finger": "middle", "key": "C"},
    {"char": "a", "hand": "left", "finger": "pinky", "key": "A"},
    {"char": "n", "hand": "right", "finger": "index", "key": "N"},
    {"char": " ", "hand": "left", "finger": "thumb", "key": "Space", "space_side": "left"},
    {"char": "w", "hand": "left", "finger": "ring", "key": "W"},
    {"char": "r", "hand": "left", "finger": "index", "key": "R"},
    {"char": "i", "hand": "right", "finger": "middle", "key": "I"},
    {"char": "t", "hand": "left", "finger": "index", "key": "T"},
    {"char": "e", "hand": "left", "finger": "middle", "key": "E"},
    {"char": " ", "hand": "right", "finger": "thumb", "key": "Space", "space_side": "right"},
    {"char": "e", "hand": "left", "finger": "middle", "key": "E"},
    {"char": "s", "hand": "left", "finger": "ring", "key": "S"},
    {"char": "s", "hand": "left", "finger": "ring", "key": "S"},
    {"char": "a", "hand": "left", "finger": "pinky", "key": "A"},
    {"char": "y", "hand": "right", "finger": "index", "key": "Y"},
    {"char": "s", "hand": "left", "finger": "ring", "key": "S"},
    {"char": " ", "hand": "right", "finger": "thumb", "key": "Space", "space_side": "right"},
    {"char": "i", "hand": "right", "finger": "middle", "key": "I"},
    {"char": "n", "hand": "right", "finger": "index", "key": "N"},
    {"char": " ", "hand": "left", "finger": "thumb", "key": "Space", "space_side": "left"},
    {"char": "m", "hand": "right", "finger": "index", "key": "M"},
    {"char": "i", "hand": "right", "finger": "middle", "key": "I"},
    {"char": "n", "hand": "right", "finger": "index", "key": "N"},
    {"char": "u", "hand": "right", "finger": "index", "key": "U"},
    {"char": "t", "hand": "left", "finger": "index", "key": "T"},
    {"char": "e", "hand": "left", "finger": "middle", "key": "E"},
    {"char": "s", "hand": "left", "finger": "ring", "key": "S"},
    {"char": ",", "hand": "right", "finger": "middle", "key": ","},
    {"char": " ", "hand": "left", "finger": "thumb", "key": "Space", "space_side": "left"},
    {"char": "s", "hand": "left", "finger": "ring", "key": "S"},
    {"char": "e", "hand": "left", "finger": "middle", "key": "E"},
    {"char": "n", "hand": "right", "finger": "index", "key": "N"},
    {"char": "d", "hand": "left", "finger": "middle", "key": "D"},
    {"char": " ", "hand": "right", "finger": "thumb", "key": "Space", "space_side": "right"},
    {"char": "m", "hand": "right", "finger": "index", "key": "M"},
    {"char": "e", "hand": "left", "finger": "middle", "key": "E"},
    {"char": "s", "hand": "left", "finger": "ring", "key": "S"},
    {"char": "s", "hand": "left", "finger": "ring", "key": "S"},
    {"char": "a", "hand": "left", "finger": "pinky", "key": "A"},
    {"char": "g", "hand": "left", "finger": "index", "key": "G"},
    {"char": "e", "hand": "left", "finger": "middle", "key": "E"},
    {"char": "s", "hand": "left", "finger": "ring", "key": "S"},
    {"char": " ", "hand": "right", "finger": "thumb", "key": "Space", "space_side": "right"},
    {"char": "f", "hand": "left", "finger": "index", "key": "F"},
    {"char": "a", "hand": "left", "finger": "pinky", "key": "A"},
    {"char": "s", "hand": "left", "finger": "ring", "key": "S"},
    {"char": "t", "hand": "left", "finger": "index", "key": "T"},
    {"char": "e", "hand": "left", "finger": "middle", "key": "E"},
    {"char": "r", "hand": "left", "finger": "index", "key": "R"},
    {"char": " ", "hand": "right", "finger": "thumb", "key": "Space", "space_side": "right"},
    {"char": "t", "hand": "left", "finger": "index", "key": "T"},
    {"char": "h", "hand": "right", "finger": "index", "key": "H"},
    {"char": "a", "hand": "left", "finger": "pinky", "key": "A"},
    {"char": "n", "hand": "right", "finger": "index", "key": "N"},
    {"char": " ", "hand": "left", "finger": "thumb", "key": "Space", "space_side": "left"},
    {"char": "y", "hand": "right", "finger": "index", "key": "Y"},
    {"char": "o", "hand": "right", "finger": "ring", "key": "O"},
    {"char": "u", "hand": "right", "finger": "index", "key": "U"},
    {"char": " ", "hand": "left", "finger": "thumb", "key": "Space", "space_side": "left"},
    {"char": "c", "hand": "left", "finger": "middle", "key": "C"},
    {"char": "a", "hand": "left", "finger": "pinky", "key": "A"},
    {"char": "n", "hand": "right", "finger": "index", "key": "N"},
    {"char": " ", "hand": "left", "finger": "thumb", "key": "Space", "space_side": "left"},
    {"char": "s", "hand": "left", "finger": "ring", "key": "S"},
    {"char": "p", "hand": "right", "finger": "pinky", "key": "P"},
    {"char": "e", "hand": "left", "finger": "middle", "key": "E"},
    {"char": "a", "hand": "left", "finger": "pinky", "key": "A"},
    {"char": "k", "hand": "right", "finger": "middle", "key": "K"},
    {"char": ",", "hand": "right", "finger": "middle", "key": ","},
    {"char": " ", "hand": "left", "finger": "thumb", "key": "Space", "space_side": "left"},
    {"char": "a", "hand": "left", "finger": "pinky", "key": "A"},
    {"char": "n", "hand": "right", "finger": "index", "key": "N"},
    {"char": "d", "hand": "left", "finger": "middle", "key": "D"},
    {"char": " ", "hand": "right", "finger": "thumb", "key": "Space", "space_side": "right"},
    {"char": "k", "hand": "right", "finger": "middle", "key": "K"},
    {"char": "e", "hand": "left", "finger": "middle", "key": "E"},
    {"char": "e", "hand": "left", "finger": "middle", "key": "E"},
    {"char": "p", "hand": "right", "finger": "pinky", "key": "P"},
    {"char": " ", "hand": "left", "finger": "thumb", "key": "Space", "space_side": "left"},
    {"char": "u", "hand": "right", "finger": "index", "key": "U"},
    {"char": "p", "hand": "right", "finger": "pinky", "key": "P"},
    {"char": " ", "hand": "left", "finger": "thumb", "key": "Space", "space_side": "left"},
    {"char": "w", "hand": "left", "finger": "ring", "key": "W"},
    {"char": "i", "hand": "right", "finger": "middle", "key": "I"},
    {"char": "t", "hand": "left", "finger": "index", "key": "T"},
    {"char": "h", "hand": "right", "finger": "index", "key": "H"},
    {"char": " ", "hand": "left", "finger": "thumb", "key": "Space", "space_side": "left"},
    {"char": "a", "hand": "left", "finger": "pinky", "key": "A"},
    {"char": "n", "hand": "right", "finger": "index", "key": "N"},
    {"char": "y", "hand": "right", "finger": "index", "key": "Y"},
    {"char": " ", "hand": "left", "finger": "thumb", "key": "Space", "space_side": "left"},
    {"char": "d", "hand": "left", "finger": "middle", "key": "D"},
    {"char": "e", "hand": "left", "finger": "middle", "key": "E"},
    {"char": "a", "hand": "left", "finger": "pinky", "key": "A"},
    {"char": "d", "hand": "left", "finger": "middle", "key": "D"},
    {"char": "l", "hand": "right", "finger": "ring", "key": "L"},
    {"char": "i", "hand": "right", "finger": "middle", "key": "I"},
    {"char": "n", "hand": "right", "finger": "index", "key": "N"},
    {"char": "e", "hand": "left", "finger": "middle", "key": "E"},
    {"char": ".", "hand": "right", "finger": "ring", "key": "."},
    {"char": " ", "hand": "left", "finger": "thumb", "key": "Space", "space_side": "left"},
    {"char": "T", "hand": "left", "finger": "index", "key": "T"},
    {"char": "h", "hand": "right", "finger": "index", "key": "H"},
    {"char": "i", "hand": "right", "finger": "middle", "key": "I"},
    {"char": "s", "hand": "left", "finger": "ring", "key": "S"},
    {"char": " ", "hand": "right", "finger": "thumb", "key": "Space", "space_side": "right"},
    {"char": "f", "hand": "left", "finger": "index", "key": "F"},
    {"char": "i", "hand": "right", "finger": "middle", "key": "I"},
    {"char": "n", "hand": "right", "finger": "index", "key": "N"},
    {"char": "a", "hand": "left", "finger": "pinky", "key": "A"},
    {"char": "l", "hand": "right", "finger": "ring", "key": "L"},
    {"char": " ", "hand": "left", "finger": "thumb", "key": "Space", "space_side": "left"},
    {"char": "p", "hand": "right", "finger": "pinky", "key": "P"},
    {"char": "a", "hand": "left", "finger": "pinky", "key": "A"},
    {"char": "s", "hand": "left", "finger": "ring", "key": "S"},
    {"char": "s", "hand": "left", "finger": "ring", "key": "S"},
    {"char": "a", "hand": "left", "finger": "pinky", "key": "A"},
    {"char": "g", "hand": "left", "finger": "index", "key": "G"},
    {"char": "e", "hand": "left", "finger": "middle", "key": "E"},
    {"char": " ", "hand": "right", "finger": "thumb", "key": "Space", "space_side": "right"},
    {"char": "i", "hand": "right", "finger": "middle", "key": "I"},
    {"char": "s", "hand": "left", "finger": "ring", "key": "S"},
    {"char": " ", "hand": "right", "finger": "thumb", "key": "Space", "space_side": "right"},
    {"char": "t", "hand": "left", "finger": "index", "key": "T"},
    {"char": "h", "hand": "right", "finger": "index", "key": "H"},
    {"char": "e", "hand": "left", "finger": "middle", "key": "E"},
    {"char": " ", "hand": "right", "finger": "thumb", "key": "Space", "space_side": "right"},
    {"char": "g", "hand": "left", "finger": "index", "key": "G"},
    {"char": "a", "hand": "left", "finger": "pinky", "key": "A"},
    {"char": "t", "hand": "left", "finger": "index", "key": "T"},
    {"char": "e", "hand": "left", "finger": "middle", "key": "E"},
    {"char": " ", "hand": "right", "finger": "thumb", "key": "Space", "space_side": "right"},
    {"char": "-", "hand": "right", "finger": "pinky", "key": "-"},
    {"char": " ", "hand": "left", "finger": "thumb", "key": "Space", "space_side": "left"},
    {"char": "l", "hand": "right", "finger": "ring", "key": "L"},
    {"char": "o", "hand": "right", "finger": "ring", "key": "O"},
    {"char": "n", "hand": "right", "finger": "index", "key": "N"},
    {"char": "g", "hand": "left", "finger": "index", "key": "G"},
    {"char": ",", "hand": "right", "finger": "middle", "key": ","},
    {"char": " ", "hand": "left", "finger": "thumb", "key": "Space", "space_side": "left"},
    {"char": "d", "hand": "left", "finger": "middle", "key": "D"},
    {"char": "e", "hand": "left", "finger": "middle", "key": "E"},
    {"char": "n", "hand": "right", "finger": "index", "key": "N"},
    {"char": "s", "hand": "left", "finger": "ring", "key": "S"},
    {"char": "e", "hand": "left", "finger": "middle", "key": "E"},
    {"char": ",", "hand": "right", "finger": "middle", "key": ","},
    {"char": " ", "hand": "left", "finger": "thumb", "key": "Space", "space_side": "left"},
    {"char": "m", "hand": "right", "finger": "index", "key": "M"},
    {"char": "i", "hand": "right", "finger": "middle", "key": "I"},
    {"char": "x", "hand": "left", "finger": "ring", "key": "X"},
    {"char": "e", "hand": "left", "finger": "middle", "key": "E"},
    {"char": "d", "hand": "left", "finger": "middle", "key": "D"},
    {"char": " ", "hand": "right", "finger": "thumb", "key": "Space", "space_side": "right"},
    {"char": "c", "hand": "left", "finger": "middle", "key": "C"},
    {"char": "o", "hand": "right", "finger": "ring", "key": "O"},
    {"char": "n", "hand": "right", "finger": "index", "key": "N"},
    {"char": "t", "hand": "left", "finger": "index", "key": "T"},
    {"char": "e", "hand": "left", "finger": "middle", "key": "E"},
    {"char": "n", "hand": "right", "finger": "index", "key": "N"},
    {"char": "t", "hand": "left", "finger": "index", "key": "T"},
    {"char": " ", "hand": "right", "finger": "thumb", "key": "Space", "space_side": "right"},
    {"char": "a", "hand": "left", "finger": "pinky", "key": "A"},
    {"char": "t", "hand": "left", "finger": "index", "key": "T"},
    {"char": " ", "hand": "right", "finger": "thumb", "key": "Space", "space_side": "right"},
    {"char": "9", "hand": "right", "finger": "ring", "key": "9"},
    {"char": "5", "hand": "left", "finger": "index", "key": "5"},
    {"char": " ", "hand": "right", "finger": "thumb", "key": "Space", "space_side": "right"},
    {"char": "W", "hand": "left", "finger": "ring", "key": "W"},
    {"char": "P", "hand": "right", "finger": "pinky", "key": "P"},
    {"char": "M", "hand": "right", "finger": "index", "key": "M"},
    {"char": ".", "hand": "right", "finger": "ring", "key": "."},
    {"char": " ", "hand": "left", "finger": "thumb", "key": "Space", "space_side": "left"},
    {"char": "P", "hand": "right", "finger": "pinky", "key": "P"},
    {"char": "a", "hand": "left", "finger": "pinky", "key": "A"},
    {"char": "s", "hand": "left", "finger": "ring", "key": "S"},
    {"char": "s", "hand": "left", "finger": "ring", "key": "S"},
    {"char": " ", "hand": "right", "finger": "thumb", "key": "Space", "space_side": "right"},
    {"char": "i", "hand": "right", "finger": "middle", "key": "I"},
    {"char": "t", "hand": "left", "finger": "index", "key": "T"},
    {"char": ",", "hand": "right", "finger": "middle", "key": ","},
    {"char": " ", "hand": "left", "finger": "thumb", "key": "Space", "space_side": "left"},
    {"char": "a", "hand": "left", "finger": "pinky", "key": "A"},
    {"char": "n", "hand": "right", "finger": "index", "key": "N"},
    {"char": "d", "hand": "left", "finger": "middle", "key": "D"},
    {"char": " ", "hand": "right", "finger": "thumb", "key": "Space", "space_side": "right"},
    {"char": "t", "hand": "left", "finger": "index", "key": "T"},
    {"char": "h", "hand": "right", "finger": "index", "key": "H"},
    {"char": "e", "hand": "left", "finger": "middle", "key": "E"},
    {"char": " ", "hand": "right", "finger": "thumb", "key": "Space", "space_side": "right"},
    {"char": "T", "hand": "left", "finger": "index", "key": "T"},
    {"char": "e", "hand": "left", "finger": "middle", "key": "E"},
    {"char": "e", "hand": "left", "finger": "middle", "key": "E"},
    {"char": "n", "hand": "right", "finger": "index", "key": "N"},
    {"char": " ", "hand": "left", "finger": "thumb", "key": "Space", "space_side": "left"},
    {"char": "M", "hand": "right", "finger": "index", "key": "M"},
    {"char": "a", "hand": "left", "finger": "pinky", "key": "A"},
    {"char": "s", "hand": "left", "finger": "ring", "key": "S"},
    {"char": "t", "hand": "left", "finger": "index", "key": "T"},
    {"char": "e", "hand": "left", "finger": "middle", "key": "E"},
    {"char": "r", "hand": "left", "finger": "index", "key": "R"},
    {"char": "y", "hand": "right", "finger": "index", "key": "Y"},
    {"char": " ", "hand": "left", "finger": "thumb", "key": "Space", "space_side": "left"},
    {"char": "c", "hand": "left", "finger": "middle", "key": "C"},
    {"char": "e", "hand": "left", "finger": "middle", "key": "E"},
    {"char": "r", "hand": "left", "finger": "index", "key": "R"},
    {"char": "t", "hand": "left", "finger": "index", "key": "T"},
    {"char": "i", "hand": "right", "finger": "middle", "key": "I"},
    {"char": "f", "hand": "left", "finger": "index", "key": "F"},
    {"char": "i", "hand": "right", "finger": "middle", "key": "I"},
    {"char": "c", "hand": "left", "finger": "middle", "key": "C"},
    {"char": "a", "hand": "left", "finger": "pinky", "key": "A"},
    {"char": "t", "hand": "left", "finger": "index", "key": "T"},
    {"char": "e", "hand": "left", "finger": "middle", "key": "E"},
    {"char": " ", "hand": "right", "finger": "thumb", "key": "Space", "space_side": "right"},
    {"char": "i", "hand": "right", "finger": "middle", "key": "I"},
    {"char": "s", "hand": "left", "finger": "ring", "key": "S"},
    {"char": " ", "hand": "right", "finger": "thumb", "key": "Space", "space_side": "right"},
    {"char": "y", "hand": "right", "finger": "index", "key": "Y"},
    {"char": "o", "hand": "right", "finger": "ring", "key": "O"},
    {"char": "u", "hand": "right", "finger": "index", "key": "U"},
    {"char": "r", "hand": "left", "finger": "index", "key": "R"},
    {"char": "s", "hand": "left", "finger": "ring", "key": "S"},
    {"char": ".", "hand": "right", "finger": "ring", "key": "."},
    {"char": " ", "hand": "left", "finger": "thumb", "key": "Space", "space_side": "left"},
    {"char": "T", "hand": "left", "finger": "index", "key": "T"},
    {"char": "y", "hand": "right", "finger": "index", "key": "Y"},
    {"char": "p", "hand": "right", "finger": "pinky", "key": "P"},
    {"char": "e", "hand": "left", "finger": "middle", "key": "E"},
    {"char": " ", "hand": "right", "finger": "thumb", "key": "Space", "space_side": "right"},
    {"char": "w", "hand": "left", "finger": "ring", "key": "W"},
    {"char": "i", "hand": "right", "finger": "middle", "key": "I"},
    {"char": "t", "hand": "left", "finger": "index", "key": "T"},
    {"char": "h", "hand": "right", "finger": "index", "key": "H"},
    {"char": " ", "hand": "left", "finger": "thumb", "key": "Space", "space_side": "left"},
    {"char": "c", "hand": "left", "finger": "middle", "key": "C"},
    {"char": "a", "hand": "left", "finger": "pinky", "key": "A"},
    {"char": "r", "hand": "left", "finger": "index", "key": "R"},
    {"char": "e", "hand": "left", "finger": "middle", "key": "E"},
    {"char": ".", "hand": "right", "finger": "ring", "key": "."}
  ],
  "keys_trained": [
    "A-Z",
    "0-9",
    "Shift",
    "Space",
    ".",
    ",",
    "-",
    ":",
    "'"
  ],
  "new_keys": [],
  "finger_focus": "Teen mastery comprehensive exam",
  "tips": [
    {
      "type": "lead",
      "text": "This is it. The teen course final. 95 WPM, one long mixed paragraph, and the certificate on the other side."
    },
    {
      "type": "drop",
      "text": "60+ WPM clean earns Gold. 80+ earns Platinum. Either way you walk out certified - aim for the tier you want."
    },
    {
      "type": "exercise",
      "target": "Seventy-five lessons ago, the keyboard was a puzzle. Today, it's an extension of your thinking. You can write essays in minutes, send messages faster than you can speak, and keep",
      "finger": "purple",
      "hint": "Teen mastery comprehensive exam"
    },
    {
      "type": "p",
      "text": "Seventy-five lessons ago the keyboard was a puzzle. Now it keeps up with your brain. Clear this and you're a certified typist - that's not a sticker, that's a skill for life. Proud of you. Now go finish it. - Jordan"
    },
    {
      "type": "callout",
      "icon": "💡",
      "title": "Подсказка",
      "text": "Slow down if you need to. Accuracy decides your cert level, not raw speed."
    },
    {
      "type": "exercise",
      "target": "up with any deadline. This final passage is the gate - long, dense, mixed content at 95 WPM. Pass it, and the Teen Mastery certificate is yours. Type with care.",
      "finger": "purple",
      "hint": "Teen mastery comprehensive exam"
    }
  ],
  "character_tips": {
    "anna": "Teen final. 75 lessons led here. Type with care - the certificate is one paragraph away.",
    "maxim": "End of the teen course. Pass and you're certified for life. Slow and steady takes it.",
    "knopych": "Final boss! One last run for the win!",
    "klavochka": "Final moment. Breathe, type, earn it. You've got this."
  },
  "phase": 5,
  "rhythmLesson": false,
  "created_at": "2026-05-25",
  "version": "1.0"
}
