{
  "id": "tier1_lesson_49",
  "tier": "tier1",
  "lesson_number": 49,
  "title": "Панграмма: классика",
  "description": "В чащах юга жил-был цитрус",
  "target_wpm": 62,
  "text_length": 109,
  "error_limit_percent": 6,
  "error_limit": 6,
  "text": "В чащах юга жил бы цитрус? Да, но фальшивый экземпляр! В чащах юга жил бы цитрус? Да, но фальшивый экземпляр!",
  "text_sequence": [],
  "keys_trained": [
    "А-Я полный",
    "Space",
    ",",
    ".",
    "?",
    "!",
    "Shift"
  ],
  "new_keys": [],
  "finger_focus": "Каждая буква хотя бы один раз",
  "tips": [
    "Русская панграмма содержит все 33 буквы",
    "Идеальный замер скорости",
    "Если делаешь 65+ WPM — печатаешь что угодно"
  ],
  "character_tips": {
    "anna": "Каждая буква, без исключений. Универсальный бенчмарк.",
    "maxim": "Сделай 5 раз — скорость должна расти с каждым разом.",
    "knopych": "ВСЕ БУКВЫ! 🦊 Цитрус найден!",
    "klavochka": "Каждая буковка здоровается, мой солнечный ☀️"
  },
  "phase": 4,
  "rhythmLesson": false,
  "created_at": "2026-05-26",
  "version": "1.0"
}