{
  "id": "en_kids_lesson_02",
  "tier": "en_kids",
  "lesson_number": 2,
  "title": "Letter S",
  "description": "Letter S — left ring finger",
  "target_wpm": 9,
  "text_length": 31,
  "error_limit_percent": 10,
  "error_limit": 3,
  "text": "s s s s s as as as sa sa sa ass",
  "text_sequence": [],
  "keys_trained": [
    "A",
    "S"
  ],
  "new_keys": [],
  "finger_focus": "Left ring finger finds S",
  "tips": [
    "S is right next to A",
    "Use your left ring finger",
    "Try \"as\" and \"sa\" — your first tiny word!"
  ],
  "character_tips": {
    "anna": "S is next to A. Try \"as\" — your first word! 🌸",
    "maxim": "Two letters now. Tiny words possible.",
    "knopych": "S unlocked! Try 'as' — that's a real word! 🌟",
    "klavochka": "Two letters, two friends, my dear! Like A and S holding hands ✨"
  },
  "phase": 1,
  "rhythmLesson": false,
  "created_at": "2026-05-25",
  "version": "1.0"
}